{
    "topic": "第38届中国电影金鸡奖",
    "total_count": 34,
    "events": [
        {
            "id": 1,
            "title": "金鸡奖确定影片参评周期",
            "summary": "第38届中国电影金鸡奖组委会规定，凡在2024年7月1日至2025年6月30日期间取得国家电影局核发的电影公映许可证的影片，方可参加本届金鸡奖评选。",
            "date": "2025年9月26日"
        },
        {
            "id": 2,
            "title": "金鸡奖完成影片征集工作",
            "summary": "第38届中国电影金鸡奖自2025年6月6日开启报名至7月7日截止，经核准共有212部符合评奖周期范围的影片进入评审资格名单。",
            "date": "2025年7月7日"
        },
        {
            "id": 3,
            "title": "金鸡百花电影节发布会召开",
            "summary": "2025年中国金鸡百花电影节发布会在北京市举行，正式官宣本届电影节将于2025年11月11日至11月15日在福建省厦门市举办。",
            "date": "2025年09月26日 上午"
        },
        {
            "id": 4,
            "title": "金鸡奖与电影节海报发布",
            "summary": "第38届中国电影金鸡奖组委会在北京发布会上，正式对外公布了第38届中国电影金鸡奖的主视觉海报以及2025年中国金鸡百花电影节的官方海报。",
            "date": "2025年09月26日"
        },
        {
            "id": 5,
            "title": "陈飞宇宋茜任金鸡推介人",
            "summary": "组委会在北京发布会上宣布电影人陈飞宇和宋茜担任“金鸡厦门”推介人，陈飞宇现场接受聘书并发表了感言。",
            "date": "2025年09月26日"
        },
        {
            "id": 6,
            "title": "金鸡奖公布奖项设置规模",
            "summary": "中国电影家协会副主席尹鸿在发布会上宣布，本届金鸡奖共设立最佳故事片、最佳中小成本故事片、评委会特别奖等共计20个奖项（含7个影片奖、12个单项奖及特别奖）。",
            "date": "2025年09月26日"
        },
        {
            "id": 7,
            "title": "金鸡奖公布最佳故事片提名",
            "summary": "评委会公布最佳故事片奖提名名单，入围影片包括《小小的我》、《长安的荔枝》、《好东西》、《志愿军：存亡之战》、《唐探1900》和《破·地狱》。",
            "date": "2025年09月26日"
        },
        {
            "id": 8,
            "title": "金鸡奖公布最佳导演提名",
            "summary": "评委会公布最佳导演奖提名名单，入围者为大鹏（《长安的荔枝》）、陈茂贤（《破·地狱》）、陈思诚与戴墨（《唐探1900》）、邵艺辉（《好东西》）、顾长卫（《刺猬》）。",
            "date": "2025年09月26日"
        },
        {
            "id": 9,
            "title": "金鸡奖公布最佳男主角提名",
            "summary": "评委会公布最佳男主角奖提名名单，入围者为大鹏（《长安的荔枝》）、朱一龙（《志愿军：存亡之战》）、刘昊然（《解密》）、易烊千玺（《小小的我》）、黄晓明（《阳光俱乐部》）。",
            "date": "2025年09月26日"
        },
        {
            "id": 10,
            "title": "金鸡奖公布最佳女主角提名",
            "summary": "评委会公布最佳女主角奖提名名单，入围者为卫诗雅（《破·地狱》）、宋佳（《好东西》）、咏梅（《出走的决心》）、段奥娟（《岁岁平安》）、徐海鹏（《但愿人长久》）。",
            "date": "2025年09月26日"
        },
        {
            "id": 11,
            "title": "金鸡奖公布最佳男配角提名",
            "summary": "评委会公布最佳男配角奖提名名单，入围者为周政杰（《老枪》）、赵又廷（《好东西》）、祖峰（《家庭简史》）、袁富华（《水饺皇后》）、耿乐（《刺猬》）。",
            "date": "2025年09月26日"
        },
        {
            "id": 12,
            "title": "金鸡奖公布最佳女配角提名",
            "summary": "评委会公布最佳女配角奖提名名单，入围者为宋晓英（《我和我母亲的疼痛》）、钟楚曦（《好东西》）、黄子琪（《小白船》）、蒋勤勤（《小小的我》）、惠英红（《水饺皇后》）。",
            "date": "2025年09月26日"
        },
        {
            "id": 13,
            "title": "金鸡奖公布最佳编剧提名",
            "summary": "评委会公布最佳编剧奖提名名单，入围者包括陈茂贤与郑纬机（《破·地狱》）、陈凯歌与张珂（《志愿军：存亡之战》）、邵艺辉（《好东西》）等。",
            "date": "2025年09月26日"
        },
        {
            "id": 14,
            "title": "金鸡奖公布导演处女作提名",
            "summary": "评委会公布最佳导演处女作奖提名名单，入围者为达杰丁增、李季、秦天、高朋、黄婷婷，涵盖《大场面》、《老枪》等影片。",
            "date": "2025年09月26日"
        },
        {
            "id": 15,
            "title": "金鸡奖公布中小成本影片提名",
            "summary": "评委会公布最佳中小成本故事片奖提名，入围影片为《小白船》、《乌龙镇》、《但愿人长久》、《我和我母亲的疼痛》和《怒江》。",
            "date": "2025年09月26日"
        },
        {
            "id": 16,
            "title": "金鸡奖公布最佳外语片提名",
            "summary": "评委会公布最佳外语片奖提名名单，入围影片包括《F1：狂飙飞车》（美国）、《此心安处》、《还有明天》、《我仍在此》及《姥姥的外孙》（泰国）。",
            "date": "2025年09月26日"
        },
        {
            "id": 17,
            "title": "金鸡奖公布美术与纪录片提名",
            "summary": "评委会公布最佳美术片（含《熊出没·重启未来》、《哪吒之魔童闹海》等）及最佳纪录/科教片（含《乡归》、《她是红线女》等）的提名名单。",
            "date": "2025年09月26日"
        },
        {
            "id": 18,
            "title": "金鸡奖公布戏曲与儿童片提名",
            "summary": "评委会公布最佳戏曲片（含京剧《锁麟囊》等）及最佳儿童片（含《不丢人》、《月光里的男孩》等）的提名名单。",
            "date": "2025年09月26日"
        },
        {
            "id": 19,
            "title": "金鸡奖公布最佳技术类提名",
            "summary": "评委会公布了最佳摄影、最佳录音、最佳美术、最佳音乐、最佳剪辑五大技术奖项的提名名单，《志愿军》、《解密》、《只此青绿》等片获多项入围。",
            "date": "2025年09月26日"
        },
        {
            "id": 20,
            "title": "两部大片领跑金鸡奖提名",
            "summary": "据统计，电影《志愿军：存亡之战》和《好东西》在提名名单中表现强势，各自获得包括最佳故事片在内的7项提名，并列成为本届提名数量最多的影片。",
            "date": "2025年09月26日"
        },
        {
            "id": 21,
            "title": "易烊千玺四冲金鸡影帝",
            "summary": "演员易烊千玺凭借电影《小小的我》入围最佳男主角，媒体报道指出这是他第四次获得金鸡奖最佳男主角提名。",
            "date": "2025年09月26日"
        },
        {
            "id": 22,
            "title": "朱一龙二度入围金鸡影帝",
            "summary": "演员朱一龙凭借在《志愿军：存亡之战》中饰演的李想一角，成功入围最佳男主角，这是他第二次获得该奖项提名。",
            "date": "2025年09月26日"
        },
        {
            "id": 23,
            "title": "黄晓明四度入围金鸡影帝",
            "summary": "演员黄晓明凭借电影《阳光俱乐部》中吴优一角入围最佳男主角，媒体指出这是他第四次获得金鸡奖最佳男主角提名，但影片尚未公映也引发了部分讨论。",
            "date": "2025年09月26日"
        },
        {
            "id": 24,
            "title": "陈思诚首获金鸡最佳导演提名",
            "summary": "陈思诚凭借电影《唐探1900》首次入围金鸡奖“最佳导演”奖，其执导的《解密》也同时获得了最佳男主角等三项技术类提名。",
            "date": "2025年09月26日"
        },
        {
            "id": 25,
            "title": "大鹏获影帝导演双重提名",
            "summary": "大鹏凭借电影《长安的荔枝》同时获得了最佳男主角和最佳导演两项重量级评委会提名，该片共斩获6项提名。",
            "date": "2025年09月26日"
        },
        {
            "id": 26,
            "title": "湖北影视作品获21项提名",
            "summary": "湖北长江电影集团联合出品的《志愿军：存亡之战》、《好东西》、《解密》等多部影片共获得21项提名，展现了湖北影视的强劲实力。",
            "date": "2025年09月26日"
        },
        {
            "id": 27,
            "title": "多位知名演员未获提名引热议",
            "summary": "提名名单公布后，杨幂、赵丽颖、章子怡等知名演员及其相关作品（如《酱园弄·悬案》）均未获提名，相关话题迅速成为网络舆论热点。",
            "date": "2025年09月26日"
        },
        {
            "id": 28,
            "title": "段奥娟提名影后引发网络热议",
            "summary": "段奥娟凭借小成本电影《岁岁平安》爆冷入围最佳女主角，话题“#段奥娟提名大爆冷#”迅速登上社交媒体热搜。",
            "date": "2025年09月26日"
        },
        {
            "id": 29,
            "title": "段奥娟发文回应金鸡奖提名",
            "summary": "段奥娟在社交媒体发文回应提名，表示既惊喜又忐忑，并感谢了金鸡奖评委会以及制片人、导演臧连荣等主创团队的信任与扶持。",
            "date": "2025年09月26日"
        },
        {
            "id": 30,
            "title": "《岁岁平安》片方透露发行困境",
            "summary": "针对入围影片《岁岁平安》未公映的情况，主创李骥接受采访表示影片因资金短缺尚未公映，团队正寻求社会资金帮助，希望争取年底公映。",
            "date": "2025年09月26日"
        },
        {
            "id": 31,
            "title": "杨幂粉丝群体因零提名动荡",
            "summary": "在杨幂未获金鸡奖提名后，媒体报道指出其粉丝群体内部出现“核心粉丝退群”、“大粉退出对接群”等动荡现象，引发关注。",
            "date": "2025年09月26日–29日"
        },
        {
            "id": 32,
            "title": "媒体解析《酱园弄》落选原因",
            "summary": "针对《酱园弄·悬案》及《乔妍的心事》零提名的情况，媒体报道引用公映许可证号指出，这些影片取证时间在2024年7月1日之前，不符合本届参评时间范围。",
            "date": "2025年09月27日"
        },
        {
            "id": 33,
            "title": "组委会公布电影节活动安排",
            "summary": "组委会宣布在11月11日至15日电影节期间，将举办包括开幕式、颁奖典礼、影展、中国电影诞生120周年座谈会等8大类50余项活动。",
            "date": "2025年09月26日"
        },
        {
            "id": 34,
            "title": "金鸡奖终评与颁奖时间确定",
            "summary": "组委会宣布第38届中国电影金鸡奖的终评将在电影节期间进行，最终获奖名单将于2025年11月15日在厦门颁奖典礼现场揭晓。",
            "date": "2025年09月26日"
        }
    ]
}